zjbbintest/__init__.py
zjbbintest/bintest.py
zjbbintest/bintest_data.py
zjbbintest/Actuator/__init__.py
zjbbintest/Actuator/bin_test_case/__init__.py
zjbbintest/Actuator/bin_test_case/bin_test_case.py
zjbbintest/Actuator/bin_test_exception/__init__.py
zjbbintest/Actuator/bin_test_exception/bin_test_exception.py
zjbbintest/Actuator/utils/__init__.py
zjbbintest/Actuator/utils/action_execution.py
zjbbintest/Actuator/utils/assert_execution.py
zjbbintest/Actuator/utils/format_check.py
zjbbintest/Actuator/utils/processing_path.py
zjbbintest/Actuator/utils/requestor.py
zjbbintest/Actuator/utils/string_dynamic_run.py
zjbbintest/Analysis/__init__.py
zjbbintest/Analysis/har2json.py
zjbbintest/Analysis/replace_values.py
zjbbintest/Template/__init__.py
zjbbintest/Template/bintest_template.py
zjbbintest/Template/report_template.html
zjbbintest-3.0.dist-info/METADATA
zjbbintest-3.0.dist-info/WHEEL
zjbbintest-3.0.dist-info/top_level.txt
zjbbintest-3.0.dist-info/RECORD
