Metadata-Version: 2.1
Name: zjbbintest
Version: 3.0
Summary: bintest自动化框架
Home-page: UNKNOWN
Author: zhangjiabin01
Author-email: zhangjiabin01@baidu.com
License: UNKNOWN
Platform: UNKNOWN
Requires-Dist: attrs (==23.2.0)
Requires-Dist: backports.tarfile (==1.1.1)
Requires-Dist: certifi (==2024.2.2)
Requires-Dist: charset-normalizer (==3.3.2)
Requires-Dist: decorator (==5.1.1)
Requires-Dist: docutils (==0.20.1)
Requires-Dist: idna (==3.7)
Requires-Dist: importlib-metadata (==7.1.0)
Requires-Dist: importlib-resources (==6.4.0)
Requires-Dist: jaraco.classes (==3.4.0)
Requires-Dist: jaraco.context (==5.3.0)
Requires-Dist: jaraco.functools (==4.0.1)
Requires-Dist: Jinja2 (==3.1.4)
Requires-Dist: jsonpath-rw (==1.4.0)
Requires-Dist: jsonschema (==4.21.1)
Requires-Dist: jsonschema-specifications (==2023.12.1)
Requires-Dist: keyring (==25.2.0)
Requires-Dist: markdown-it-py (==3.0.0)
Requires-Dist: MarkupSafe (==2.1.5)
Requires-Dist: mdurl (==0.1.2)
Requires-Dist: more-itertools (==10.2.0)
Requires-Dist: nh3 (==0.2.17)
Requires-Dist: pkginfo (==1.10.0)
Requires-Dist: pkgutil-resolve-name (==1.3.10)
Requires-Dist: ply (==3.11)
Requires-Dist: Pygments (==2.18.0)
Requires-Dist: readme-renderer (==43.0)
Requires-Dist: referencing (==0.34.0)
Requires-Dist: requests (==2.31.0)
Requires-Dist: requests-toolbelt (==1.0.0)
Requires-Dist: rfc3986 (==2.0.0)
Requires-Dist: rich (==13.7.1)
Requires-Dist: rpds-py (==0.18.0)
Requires-Dist: six (==1.16.0)
Requires-Dist: twine (==5.0.0)
Requires-Dist: typing-extensions (==4.11.0)
Requires-Dist: urllib3 (==2.2.1)
Requires-Dist: zipp (==3.18.1)
